Metadata-Version: 2.1
Name: modulo-data-bot
Version: 0.1
Summary: Modulo para crear la base de datos de KCK_BOT_SV
Author: Gerardo Loucel
License-File: licence.txt
